automatic_speech_recognition/__init__.py
automatic_speech_recognition/augmentation/__init__.py
automatic_speech_recognition/augmentation/augmentation.py
automatic_speech_recognition/augmentation/spec_augment.py
automatic_speech_recognition/callback/__init__.py
automatic_speech_recognition/callback/batch_logger.py
automatic_speech_recognition/callback/distributed_model_checkpoint.py
automatic_speech_recognition/dataset/__init__.py
automatic_speech_recognition/dataset/audio.py
automatic_speech_recognition/dataset/dataset.py
automatic_speech_recognition/dataset/features.py
automatic_speech_recognition/decoder/__init__.py
automatic_speech_recognition/decoder/decoder.py
automatic_speech_recognition/evaluate/__init__.py
automatic_speech_recognition/evaluate/activations.py
automatic_speech_recognition/evaluate/distance.py
automatic_speech_recognition/evaluate/evaluate.py
automatic_speech_recognition/features/__init__.py
automatic_speech_recognition/features/feature_extractor.py
automatic_speech_recognition/features/filter_banks.py
automatic_speech_recognition/features/spectrogram.py
automatic_speech_recognition/load/__init__.py
automatic_speech_recognition/load/load.py
automatic_speech_recognition/model/__init__.py
automatic_speech_recognition/model/deepspeech.py
automatic_speech_recognition/model/deepspeech2.py
automatic_speech_recognition/pipeline/__init__.py
automatic_speech_recognition/pipeline/ctc_pipeline.py
automatic_speech_recognition/pipeline/pipeline.py
automatic_speech_recognition/text/__init__.py
automatic_speech_recognition/text/alphabet-en.txt
automatic_speech_recognition/text/alphabet-pl.txt
automatic_speech_recognition/text/alphabet.py
automatic_speech_recognition/utils/__init__.py
automatic_speech_recognition/utils/consumer.py
automatic_speech_recognition/utils/utils.py
automatic_speech_recognition-1.0.4.dist-info/LICENSE.md
automatic_speech_recognition-1.0.4.dist-info/METADATA
automatic_speech_recognition-1.0.4.dist-info/WHEEL
automatic_speech_recognition-1.0.4.dist-info/top_level.txt
automatic_speech_recognition-1.0.4.dist-info/RECORD
