Metadata-Version: 2.1
Name: automatic-speech-recognition
Version: 1.0.4
Summary: Distill the Automatic Speech Recognition (TensorFlow)
Home-page: https://github.com/rolczynski/Automatic-Speech-Recognition
Author: Rolczynski Rafal
Author-email: rafal.rolczynski@gmail.com
License: GNU
Platform: UNKNOWN
Requires-Python: ~=3.7
Requires-Dist: tensorflow (>=2.0)
Requires-Dist: pandas
Requires-Dist: tables
Requires-Dist: scipy
Requires-Dist: google-cloud-storage
Requires-Dist: python-speech-features
